compmec/nurbs/__classes__.py
compmec/nurbs/__init__.py
compmec/nurbs/advanced.py
compmec/nurbs/calculus.py
compmec/nurbs/curves.py
compmec/nurbs/functions.py
compmec/nurbs/heavy.py
compmec/nurbs/knotspace.py
compmec_nurbs-1.0.8.dist-info/LICENSE.md
compmec_nurbs-1.0.8.dist-info/METADATA
compmec_nurbs-1.0.8.dist-info/WHEEL
compmec_nurbs-1.0.8.dist-info/RECORD
